[
    {
        "question_number": 1,
        "question": "Q1. 23 x 20",
        "student_answer": "460"
    },
    {
        "question_number": 2,
        "question": "Q2. 24 x 20",
        "student_answer": "480"
    },
    {
        "question_number": 3,
        "question": "Q3. 25 x 20",
        "student_answer": "500"
    },
    {
        "question_number": 4,
        "question": "Q4. 26 x 20",
        "student_answer": "520"
    },
    {
        "question_number": 5,
        "question": "Q5. 27 x 20",
        "student_answer": "540"
    },
    {
        "question_number": 6,
        "question": "Q6. 34 x 20",
        "student_answer": "560"
    },
    {
        "question_number": 7,
        "question": "Q7. 35 x 20",
        "student_answer": "570"
    },
    {
        "question_number": 8,
        "question": "Q8. 36 x 20",
        "student_answer": "580"
    },
    {
        "question_number": 9,
        "question": "Q9. 37 x 20",
        "student_answer": "590"
    },
    {
        "question_number": 10,
        "question": "Q10. 38 x 20",
        "student_answer": "500"
    },
    {
        "question_number": 11,
        "question": "Q11. 48 x 20",
        "student_answer": "600"
    },
    {
        "question_number": 12,
        "question": "Q12. 49 x 20",
        "student_answer": "710"
    },
    {
        "question_number": 13,
        "question": "Q13. 50 x 20",
        "student_answer": "720"
    },
    {
        "question_number": 14,
        "question": "Q14. 51 x 20",
        "student_answer": "730"
    },
    {
        "question_number": 15,
        "question": "Q15. 52 x 20",
        "student_answer": "740"
    },
    {
        "question_number": 16,
        "question": "Q16. 59 x 20",
        "student_answer": "710"
    },
    {
        "question_number": 17,
        "question": "Q17. 60 x 20",
        "student_answer": "820"
    },
    {
        "question_number": 18,
        "question": "Q18. 61 x 20",
        "student_answer": "830"
    },
    {
        "question_number": 19,
        "question": "Q19. 62 x 20",
        "student_answer": "840"
    },
    {
        "question_number": 20,
        "question": "Q20. 63 x 20",
        "student_answer": "850"
    },
    {
        "question_number": 21,
        "question": "Q21. 77 x 20",
        "student_answer": "990"
    },
    {
        "question_number": 22,
        "question": "Q22. 78 x 20",
        "student_answer": "900"
    },
    {
        "question_number": 23,
        "question": "Q23. 79 x 20",
        "student_answer": "710"
    },
    {
        "question_number": 24,
        "question": "Q24. 80 x 20",
        "student_answer": "020"
    },
    {
        "question_number": 25,
        "question": "Q25. 81 x 20",
        "student_answer": "130"
    },
    {
        "question_number": 26,
        "question": "Q26. 26 x 20",
        "student_answer": "480"
    },
    {
        "question_number": 27,
        "question": "Q27. 27 x 20",
        "student_answer": "490"
    },
    {
        "question_number": 28,
        "question": "Q28. 28 x 20",
        "student_answer": "500"
    },
    {
        "question_number": 29,
        "question": "Q29. 29 x 20",
        "student_answer": "510"
    },
    {
        "question_number": 30,
        "question": "Q30. 30 x 20",
        "student_answer": "520"
    },
    {
        "question_number": 31,
        "question": "Q31. 41 x 20",
        "student_answer": "630"
    },
    {
        "question_number": 32,
        "question": "Q32. 42 x 20",
        "student_answer": "640"
    },
    {
        "question_number": 33,
        "question": "Q33. 43 x 20",
        "student_answer": "650"
    },
    {
        "question_number": 34,
        "question": "Q34. 44 x 20",
        "student_answer": "660"
    },
    {
        "question_number": 35,
        "question": "Q35. 45 x 20",
        "student_answer": "670"
    },
    {
        "question_number": 36,
        "question": "Q36. 91 x 20",
        "student_answer": "1130"
    },
    {
        "question_number": 37,
        "question": "Q37. 92 x 20",
        "student_answer": "240"
    },
    {
        "question_number": 38,
        "question": "Q38. 93 x 20",
        "student_answer": "250"
    },
    {
        "question_number": 39,
        "question": "Q39. 94 x 20",
        "student_answer": "260"
    },
    {
        "question_number": 40,
        "question": "Q40. 95 x 20",
        "student_answer": "170"
    }
]